volumito/__init__.py
volumito/cli/__init__.py
volumito/cli/volumito.py
volumito/clients/__init__.py
volumito/clients/errors.py
volumito/clients/mpd/__init__.py
volumito/clients/mpd/client.py
volumito/clients/rest/__init__.py
volumito/clients/rest/client.py
volumito-0.0.1.dist-info/licenses/LICENSE
volumito-0.0.1.dist-info/METADATA
volumito-0.0.1.dist-info/WHEEL
volumito-0.0.1.dist-info/entry_points.txt
volumito-0.0.1.dist-info/top_level.txt
volumito-0.0.1.dist-info/RECORD
